<link-config>
	<link src="00:00:00:00:00:00:00:03" dst="00:00:00:00:00:00:00:02" capacity="40" cost="5"/>
	<link src="00:00:00:00:00:00:00:02" dst="00:00:00:00:00:00:00:03" capacity="40" cost="5"/>

	<link src="00:00:00:00:00:00:00:01" dst="00:00:00:00:00:00:00:02" capacity="50" cost="5"/>
	<link src="00:00:00:00:00:00:00:02" dst="00:00:00:00:00:00:00:01" capacity="50" cost="5"/>

	<link src="00:00:00:00:00:00:00:03" dst="00:00:00:00:00:00:00:01" capacity="50" cost="5"/>
	<link src="00:00:00:00:00:00:00:01" dst="00:00:00:00:00:00:00:03" capacity="50" cost="5"/>
    
	<link src="10.0.0.2" dst="00:00:00:00:00:00:00:02" capacity="100" cost="0"/>
	<link src="00:00:00:00:00:00:00:02" dst="10.0.0.2" capacity="100" cost="0"/>

	<link src="10.0.0.3" dst="00:00:00:00:00:00:00:01" capacity="100" cost="0"/>
	<link src="00:00:00:00:00:00:00:01" dst="10.0.0.3" capacity="100" cost="0"/>

	<link src="10.0.0.1" dst="00:00:00:00:00:00:00:01" capacity="100" cost="0"/>
	<link src="00:00:00:00:00:00:00:01" dst="10.0.0.1" capacity="100" cost="0"/>
</link-config>